{"cameraMode":{"drawMode":0,"name":"Shaded","section":"Shading Mode"},"sceneLighting":true,"audioPlay":false,"sceneViewState":{"m_AlwaysRefresh":false,"showFog":true,"showSkybox":true,"showFlares":true,"showImageEffects":true,"showParticleSystems":true,"showVisualEffectGraphs":true,"m_FxEnabled":true},"in2DMode":false,"pivot":{"x":0.0,"y":5.0,"z":0.0},"rotation":{"x":-0.09633082151412964,"y":0.8881550431251526,"z":-0.217637836933136,"w":-0.39311474561691286},"size":12.12435531616211,"orthographic":false}